simulacra_summarizer/__init__.py
simulacra_summarizer/main.py
simulacra_summarizer/prompts.py
simulacra_summarizer-2025.12.21100341.dist-info/METADATA
simulacra_summarizer-2025.12.21100341.dist-info/WHEEL
simulacra_summarizer-2025.12.21100341.dist-info/top_level.txt
simulacra_summarizer-2025.12.21100341.dist-info/RECORD
