Metadata-Version: 2.4
Name: simulacra-summarizer
Version: 2025.12.21100341
Summary: A new package would provide a structured, reliable way to analyze and summarize user-provided text on topics like the simulation hypothesis, using an LLM to generate concise, pattern-validated outputs
Author-email: simulacra-summarizer <hi@eugene.plus>
License: MIT
Project-URL: Homepage, https://github.com/chigwell/simulacra-summarizer
Requires-Python: >=3.9
Requires-Dist: langchain-llm7>=0.0.0
Requires-Dist: llmatch-messages>=0.0.0
Requires-Dist: langchain-core>=0.3.0
